pitcher/__init__.py
pitcher/application.py
pitcher/converters.py
pitcher/exceptions.py
pitcher/middleware.py
pitcher/request.py
pitcher/response.py
pitcher/router.py
pitcher/serializable.py
tests/functional/__init__.py
tests/functional/conftest.py
tests/functional/test_exceptions.py
tests/functional/test_hello.py
tests/functional/test_middleware.py
tests/functional/test_path_params.py
tests/functional/test_requests.py
tests/functional/test_responses.py
tests/functional/test_routing.py
pitcher-0.0.1.dist-info/LICENSE
pitcher-0.0.1.dist-info/METADATA
pitcher-0.0.1.dist-info/WHEEL
pitcher-0.0.1.dist-info/top_level.txt
pitcher-0.0.1.dist-info/RECORD
