Metadata-Version: 2.1
Name: pitcher
Version: 0.0.1
Summary: Python web framework for API Gateway
Home-page: https://github.com/twobulls/pitcher
Author: Ben Kersten
Author-email: ben.kersten@twobulls.com
License: MIT
Platform: UNKNOWN
Classifier: Programming Language :: Python :: 3
Classifier: License :: OSI Approved :: MIT License
Classifier: Operating System :: OS Independent
Requires-Python: >=3.7
